jsCalc/app.py
jsbCalc/__init__.py
jsbCalc/app.py
jsbCalc-0.0.6.dist-info/LICENSE
jsbCalc-0.0.6.dist-info/METADATA
jsbCalc-0.0.6.dist-info/WHEEL
jsbCalc-0.0.6.dist-info/top_level.txt
jsbCalc-0.0.6.dist-info/RECORD
