Metadata-Version: 2.1
Name: jsbCalc
Version: 0.0.6
Summary: my calculator
Author: junsu bae
Author-email: hashilyze@gmail.com
Keywords: jsbCalc,jsb,calc
Classifier: Programming Language :: Python :: 3
License-File: LICENSE
